Metadata-Version: 2.1
Name: nanoinsight
Version: 0.0.3
Summary: Repeat annotation tool for insertions called by NanoVar
Home-page: https://github.com/AsmaaSamyMohamedMahmoud/nanoinsight
Author: Asmaa
Author-email: asmmahmoud@mun.ca
License: gpl-3.0
Keywords: insertion,structural variant,repeat annotation
Classifier: Operating System :: POSIX :: Linux
Classifier: Programming Language :: Python :: 3.8
Classifier: License :: OSI Approved :: GNU General Public License v3 (GPLv3)
Classifier: Topic :: Scientific/Engineering :: Bio-Informatics
Requires-Python: >=3.8
Requires-Dist: biopython>=1.82
Requires-Dist: scikit-allel>=1.3.7
Requires-Dist: pandas>=1.5.3
